micronet/__init__.py
micronet/base_module/__init__.py
micronet/base_module/op.py
micronet/compression/__init__.py
micronet/compression/pruning/__init__.py
micronet/compression/pruning/gc_prune.py
micronet/compression/pruning/main.py
micronet/compression/pruning/normal_regular_prune.py
micronet/compression/quantization/__init__.py
micronet/compression/quantization/wbwtab/__init__.py
micronet/compression/quantization/wbwtab/main.py
micronet/compression/quantization/wbwtab/quantize.py
micronet/compression/quantization/wqaq/__init__.py
micronet/compression/quantization/wqaq/dorefa/__init__.py
micronet/compression/quantization/wqaq/dorefa/main.py
micronet/compression/quantization/wqaq/dorefa/quantize.py
micronet/compression/quantization/wqaq/iao/__init__.py
micronet/compression/quantization/wqaq/iao/main.py
micronet/compression/quantization/wqaq/iao/quantize.py
micronet/deploy/__init__.py
micronet/deploy/tensorrt/__init__.py
micronet/deploy/tensorrt/calibrator.py
micronet/deploy/tensorrt/eval_trt.py
micronet/deploy/tensorrt/test_trt.py
micronet/deploy/tensorrt/util_trt.py
micronet/deploy/tensorrt/models/__init__.py
micronet/deploy/tensorrt/models/models_trt.py
micronet/models/__init__.py
micronet/models/nin.py
micronet/models/nin_gc.py
micronet/models/resnet.py
micronet-1.12.0.dist-info/LICENSE
micronet-1.12.0.dist-info/METADATA
micronet-1.12.0.dist-info/WHEEL
micronet-1.12.0.dist-info/top_level.txt
micronet-1.12.0.dist-info/RECORD
