Metadata-Version: 2.1
Name: micronet
Version: 1.12.0
Summary: A model compression and deploy lib.
Home-page: https://github.com/666DZY666/micronet
Author: 666DZY666
Author-email: dzy_pku@pku.edu.cn
License: UNKNOWN
Platform: UNKNOWN
Classifier: Programming Language :: Python :: 3 :: Only
Classifier: License :: OSI Approved :: MIT License
Classifier: Operating System :: OS Independent
Requires-Python: >=3.6
Requires-Dist: torch (>=1.1.0)
Requires-Dist: torchvision
Requires-Dist: numpy
